{
  "name": "t:sections.footer.name",
  "type": "footer",
  "sections": {
    "footer": {
      "type": "footer",
      "blocks": {
        "a9e04ed8-425e-4c01-9678-be73f0638243": {
          "type": "image",
          "settings": {
            "image": "shopify:\/\/shop_images\/Group.png",
            "image_width": 300,
            "alignment": ""
          }
        },
        "978d6168-bbb2-440b-8b16-e6e59b48f3a8": {
          "type": "itom_link",
          "settings": {
            "button_label_1": "CONTACT",
            "button_link_1": "shopify:\/\/pages\/weekly-videos",
            "email": "<p>resources@milestonechurch.com<\/p>",
            "phone": "<p>817-812-3600<\/p>"
          }
        },
        "34a2522c-80be-4022-b7fd-8fa0b7b50bf9": {
          "type": "link_list",
          "settings": {
            "heading": "<a href=\"\/pages\/books\" title=\"Books\">BOOKS<\/a>",
            "menu": "books"
          }
        },
        "2c6ea17f-b406-409b-ad24-5b7eeb5dd23f": {
          "type": "link_list",
          "settings": {
            "heading": "<a href=\"\/pages\/study-guides\" title=\"Study Guides\">Study Guides<\/a>",
            "menu": "study-guides"
          }
        },
        "7b5fae92-4b5c-40fd-9ab3-b591b9641a50": {
          "type": "link_list",
          "settings": {
            "heading": "<a href=\"\/pages\/music\" title=\"Music\">MUSIC<\/a>",
            "menu": "music"
          }
        },
        "39bfe5ca-8ad0-4f3d-ae5d-296ed6134552": {
          "type": "itoms_link",
          "settings": {
            "button_label_2": "Milestone Church",
            "button_link_2": "https:\/\/milestonechurch.com\/"
          }
        }
      },
      "block_order": [
        "a9e04ed8-425e-4c01-9678-be73f0638243",
        "978d6168-bbb2-440b-8b16-e6e59b48f3a8",
        "34a2522c-80be-4022-b7fd-8fa0b7b50bf9",
        "2c6ea17f-b406-409b-ad24-5b7eeb5dd23f",
        "7b5fae92-4b5c-40fd-9ab3-b591b9641a50",
        "39bfe5ca-8ad0-4f3d-ae5d-296ed6134552"
      ],
      "settings": {
        "color_scheme": "background-1",
        "newsletter_enable": false,
        "newsletter_heading": "Subscribe to our emails",
        "enable_follow_on_shop": false,
        "show_social": true,
        "enable_country_selector": true,
        "enable_language_selector": true,
        "payment_enable": false,
        "show_policy": true,
        "margin_top": 0,
        "padding_top": 59,
        "padding_bottom": 32,
        "link_page_terms_use": "shopify:\/\/pages\/terms-of-use",
        "link_page_police": "shopify:\/\/pages\/privacy-policy"
      }
    }
  },
  "order": [
    "footer"
  ]
}